LICENSE
README.md
setup.py
hubspain/__init__.py
hubspain/generation.py
hubspain.egg-info/PKG-INFO
hubspain.egg-info/SOURCES.txt
hubspain.egg-info/dependency_links.txt
hubspain.egg-info/requires.txt
hubspain.egg-info/top_level.txt